pysmarlaapi/__init__.py
pysmarlaapi/classes/__init__.py
pysmarlaapi/classes/auth_token.py
pysmarlaapi/classes/connection.py
pysmarlaapi/connection_hub/__init__.py
pysmarlaapi/federwiege/__init__.py
pysmarlaapi/federwiege/classes/__init__.py
pysmarlaapi/federwiege/classes/property.py
pysmarlaapi/federwiege/classes/service.py
pysmarlaapi/federwiege/services/__init__.py
pysmarlaapi/federwiege/services/analyser_service.py
pysmarlaapi/federwiege/services/babywiege_service.py
pysmarlaapi/federwiege/services/info_service.py
pysmarlaapi-0.9.3.dist-info/licenses/LICENSE
pysmarlaapi-0.9.3.dist-info/WHEEL
pysmarlaapi-0.9.3.dist-info/METADATA
pysmarlaapi-0.9.3.dist-info/RECORD
