Metadata-Version: 2.4
Name: pysmarlaapi
Version: 0.9.3
Summary: Swing2Sleep Smarla API
Author-email: Robin Lintermann <robin.lintermann@explicatis.com>
Requires-Python: >=3.11
License-Expression: Apache-2.0
Classifier: Programming Language :: Python :: 3
Classifier: Programming Language :: Python :: 3.11
Classifier: Programming Language :: Python :: 3.12
Classifier: Programming Language :: Python :: 3.13
License-File: LICENSE
Requires-Dist: aiohttp>=3.11
Requires-Dist: jsonpickle>=4.0.0
Requires-Dist: pysignalr>=1.3.0
Project-URL: Issues, https://github.com/Explicatis-GmbH/pysmarlaapi/issues
Project-URL: Repository, https://github.com/Explicatis-GmbH/pysmarlaapi
